sprkBE103cit/ECDF.py
sprkBE103cit/__init__.py
sprkBE103cit/labeling_ecdf_comparison.py
sprkBE103cit-0.0.2.dist-info/LICENSE.txt
sprkBE103cit-0.0.2.dist-info/METADATA
sprkBE103cit-0.0.2.dist-info/WHEEL
sprkBE103cit-0.0.2.dist-info/top_level.txt
sprkBE103cit-0.0.2.dist-info/RECORD
